aliasify/__init__.py
aliasify/_entity_replacer.py
aliasify/main.py
aliasify-0.0.3.dist-info/LICENSE
aliasify-0.0.3.dist-info/METADATA
aliasify-0.0.3.dist-info/WHEEL
aliasify-0.0.3.dist-info/entry_points.txt
aliasify-0.0.3.dist-info/top_level.txt
aliasify-0.0.3.dist-info/RECORD
