Metadata-Version: 2.1
Name: aliasify
Version: 0.0.3
Summary: Replaces all entities in a text with aliases, so that you can ask chatGPT to modify your text without revealing confidential information. After chatGPT has modified your text, the aliases can be restored again.
Author-email: Stephan Probst <stephan.probst@qurios-it.de>, Qurios IT GmbH <info@qurios-it.de>
License: MIT License
Project-URL: Homepage, https://github.com/qurios-it/aliasify
Project-URL: repository, https://github.com/qurios-it/aliasify
Keywords: chatGPT
Classifier: License :: OSI Approved :: MIT License
Classifier: Programming Language :: Python :: 3
License-File: LICENSE
Requires-Dist: pynput (>=1.7.6)
Requires-Dist: pyperclip (>=1.8.2)
Requires-Dist: spacy (>=3.5.0)
Requires-Dist: win10toast (>=0.9)
Provides-Extra: dev
Requires-Dist: pylint (==2.16.2) ; extra == 'dev'
Requires-Dist: black (==23.1.0) ; extra == 'dev'
